Workbook
Name aporte: Simulador!$E$15
Name patrimonio: Simulador!$E$18
Name perfil: Simulador!$C$28
Name periodo: Simulador!$E$16
Name porcentual_sal: Simulador!$C$12
Name rendimento: Simulador!$C$11
Name salario: Simulador!$C$10
Name taxa: Simulador!$E$17

Sheet Simulador
B9: PARÂMETROS
B10: Qual é o seu salário? | C10: 2000
B11: Qual é o rendimento da carteira? | C11: 0.006
B12: Qual o porcentual investido do Salário? | C12: 0.3 | D12: =salario*porcentual_sal -> 600
B14: INVESTIMENTO MENSAL
B15: Quanto investir por mês? | E15: 200
B16: Por Quantos Anos? | E16: 5
B17: Taxa de Rendimento mensal? | E17: 0.01079
B18: Patrimônio acumulado= | E18: =FV(taxa,periodo*12,aporte*-1) -> 16755.383
B19: Dividendos Mensais= | E19: =patrimonio*rendimento -> 100.5323
B21: PREVISÃO | E21: Dividendos
A22: 2 | B22: Quanto de patrimônio em 2 Anos? | D22: =FV(taxa,A22*12,aporte*-1) -> 5445.5255 | E22: =D22*rendimento -> 32.673153
A23: 5 | B23: Quanto de patrimônio em 5 Anos? | D23: =FV(taxa,A23*12,aporte*-1) -> 16755.383 | E23: =D23*rendimento -> 100.5323
A24: 10 | B24: Quanto de patrimônio em 10 Anos? | D24: =FV(taxa,A24*12,aporte*-1) -> 48656.843 | E24: =D24*rendimento -> 291.94106
A25: 20 | B25: Quanto de patrimônio em 20 Anos? | D25: =FV(taxa,A25*12,aporte*-1) -> 225039.68 | E25: =D25*rendimento -> 1350.2381
A26: 30 | B26: Quanto de patrimônio em 30 Anos? | D26: =FV(taxa,A26*12,aporte*-1) -> 864433.93 | E26: =D26*rendimento -> 5186.6036
B28: PERFIL | C28: Conservador
B29: VALOR A SER INVESTIDO POR MÊS | C29: =aporte -> 200
B31: TIPO DE FII | C31: Percentual Sugerido | E31: Valores
B32: PAPEL | C32: =VLOOKUP(perfil&"-"&B32,Dados!$B3:$E20,4,FALSE) -> 0.3 | E32: =C32*$C$29 -> 60
B33: TIJOLO | C33: =VLOOKUP(perfil&"-"&B33,Dados!$B4:$E21,4,FALSE) -> 0.5 | E33: =C33*$C$29 -> 100
B34: HÍBRIDOS | C34: =VLOOKUP(perfil&"-"&B34,Dados!$B5:$E22,4,FALSE) -> 0.1 | E34: =C34*$C$29 -> 20
B35: FOFs | C35: =VLOOKUP(perfil&"-"&B35,Dados!$B6:$E23,4,FALSE) -> 0.1 | E35: =C35*$C$29 -> 20
B36: DESENVOLVIMENTO | C36: =VLOOKUP(perfil&"-"&B36,Dados!$B7:$E24,4,FALSE) -> 0 | E36: =C36*$C$29 -> 0
B37: HOTELARIAS | C37: =VLOOKUP(perfil&"-"&B37,Dados!$B8:$E25,4,FALSE) -> 0 | E37: =C37*$C$29 -> 0
E38: =SUM(E32:E37) -> 200

Sheet Dados
B2: CHAVE | C2: PERFIL | D2: TIPO DE FII | E2: %
B3: Conservador-PAPEL | C3: Conservador | D3: PAPEL | E3: 0.3
B4: Conservador-TIJOLO | C4: Conservador | D4: TIJOLO | E4: 0.5
B5: Conservador-HÍBRIDOS | C5: Conservador | D5: HÍBRIDOS | E5: 0.1
B6: Conservador-FOFs | C6: Conservador | D6: FOFs | E6: 0.1
B7: Conservador-DESENVOLVIMENTO | C7: Conservador | D7: DESENVOLVIMENTO | E7: 0
B8: Conservador-HOTELARIAS | C8: Conservador | D8: HOTELARIAS | E8: 0
B9: Moderado-PAPEL | C9: Moderado | D9: PAPEL | E9: 0.32
B10: Moderado-TIJOLO | C10: Moderado | D10: TIJOLO | E10: 0.35
B11: Moderado-HÍBRIDOS | C11: Moderado | D11: HÍBRIDOS | E11: 0.08
B12: Moderado-FOFs | C12: Moderado | D12: FOFs | E12: 0.05
B13: Moderado-DESENVOLVIMENTO | C13: Moderado | D13: DESENVOLVIMENTO | E13: 0.1
B14: Moderado-HOTELARIAS | C14: Moderado | D14: HOTELARIAS | E14: 0.1
... B20: Agressivo-HOTELARIAS | C20: Agressivo | D20: HOTELARIAS | E20: 0.1
